threefive3/__init__.py
threefive3/aac.py
threefive3/base.py
threefive3/bitn.py
threefive3/commands.py
threefive3/crc.py
threefive3/cue.py
threefive3/descriptors.py
threefive3/encode.py
threefive3/gums.py
threefive3/hls.py
threefive3/hlstags.py
threefive3/iframes.py
threefive3/new_reader.py
threefive3/packetdata.py
threefive3/pmt.py
threefive3/section.py
threefive3/segment.py
threefive3/segmentation.py
threefive3/sixfix.py
threefive3/stream.py
threefive3/streamtypes.py
threefive3/stuff.py
threefive3/superkabuki.py
threefive3/upids.py
threefive3/uxp.py
threefive3/version.py
threefive3/words.py
threefive3/xml.py
threefive3-3.0.45.data/scripts/threefive3
threefive3-3.0.45.dist-info/LICENSE
threefive3-3.0.45.dist-info/METADATA
threefive3-3.0.45.dist-info/WHEEL
threefive3-3.0.45.dist-info/top_level.txt
threefive3-3.0.45.dist-info/RECORD
