Metadata-Version: 2.1
Name: threefive3
Version: 3.0.45
Summary: SCTE-35 decoder and encoder with MPEGTS and HLS and XML support.
Home-page: https://github.com/superkabuki/threefive3
Author: Adrian of Doom
Author-email: spam@iodisco.com
Classifier: License :: OSI Approved :: Sleepycat License
Classifier: Environment :: Console
Classifier: Operating System :: OS Independent
Classifier: Operating System :: POSIX :: BSD :: OpenBSD
Classifier: Operating System :: POSIX :: BSD :: NetBSD
Classifier: Operating System :: POSIX :: Linux
Classifier: Topic :: Multimedia :: Video
Classifier: Programming Language :: Python :: 3.6
Classifier: Programming Language :: Python :: Implementation :: PyPy
Classifier: Programming Language :: Python :: Implementation :: CPython
Requires-Python: >=3.6
License-File: LICENSE
Requires-Dist: pyaes
